Metadata-Version: 2.1
Name: mcsquare
Version: 1.0
Summary: Testing pictures for MonteCarlo algoritm
Home-page: UNKNOWN
Author-email: 9195049991@mail.ru
License: UNKNOWN
Platform: UNKNOWN
